freeplay_server/__init__.py
freeplay_server/__main__.py
freeplay_server/accounts/__init__.py
freeplay_server/accounts/account_creator.py
freeplay_server/accounts/account_show_page.py
freeplay_server/accounts/accounts_blueprint_filters.py
freeplay_server/accounts/accounts_repository.py
freeplay_server/accounts/default_administration.py
freeplay_server/accounts/user_creator.py
freeplay_server/accounts/users.py
freeplay_server/app.py
freeplay_server/app_environment.py
freeplay_server/auth/__init__.py
freeplay_server/auth/api_key_service.py
freeplay_server/auth/api_keys_repository.py
freeplay_server/auth/auth_filter.py
freeplay_server/comparisons/__init__.py
freeplay_server/comparisons/comparisons.py
freeplay_server/comparisons/comparisons_page.py
freeplay_server/comparisons/comparisons_service.py
freeplay_server/database_support/__init__.py
freeplay_server/database_support/database_decoding.py
freeplay_server/database_support/database_gateway.py
freeplay_server/evaluations/__init__.py
freeplay_server/evaluations/auto_eval_criteria_formatter.py
freeplay_server/evaluations/auto_eval_errors.py
freeplay_server/evaluations/auto_eval_processor.py
freeplay_server/evaluations/eval_page.py
freeplay_server/evaluations/evaluations_repository.py
freeplay_server/extensions.py
freeplay_server/health_api.py
freeplay_server/login/__init__.py
freeplay_server/login/login_page.py
freeplay_server/models.py
freeplay_server/monitoring/__init__.py
freeplay_server/monitoring/datadog_client.py
freeplay_server/project_sessions/__init__.py
freeplay_server/project_sessions/project_session_creator.py
freeplay_server/project_sessions/project_sessions.py
freeplay_server/project_sessions/project_sessions_api.py
freeplay_server/project_sessions/project_sessions_page.py
freeplay_server/project_sessions/project_sessions_repository.py
freeplay_server/project_sessions/prompt_model.py
freeplay_server/project_sessions/session_display_service.py
freeplay_server/project_sessions/test_builders.py
freeplay_server-0.1.0.dist-info/METADATA
freeplay_server-0.1.0.dist-info/WHEEL
freeplay_server-0.1.0.dist-info/RECORD
