Metadata-Version: 2.1
Name: freeplay_server
Version: 0.1.0
Summary: 
Author: Eric Ryan
Author-email: ewryan@gmail.com
Requires-Python: >=3.11,<4.0
Classifier: Programming Language :: Python :: 3
Classifier: Programming Language :: Python :: 3.11
Requires-Dist: alembic (>=1.10.2,<2.0.0)
Requires-Dist: anthropic (>=0.2.10,<0.3.0)
Requires-Dist: argon2-cffi (==23.1.0)
Requires-Dist: dacite (>=1.8.0,<2.0.0)
Requires-Dist: datadog (>=0.45.0,<0.46.0)
Requires-Dist: flask (>=2.2.3,<3.0.0)
Requires-Dist: flask-session (==0.5.0)
Requires-Dist: flask-sqlalchemy (>=3.0.3,<4.0.0)
Requires-Dist: flask-swagger-ui (>=4.11.1,<5.0.0)
Requires-Dist: freeplay (>=0.2.12,<0.3.0)
Requires-Dist: gunicorn (>=20.1.0,<21.0.0)
Requires-Dist: mypy (==1.4.1)
Requires-Dist: openai (>=0.27.4,<0.28.0)
Requires-Dist: parse (>=1.19.0,<2.0.0)
Requires-Dist: psycopg2 (>=2.9.6,<3.0.0)
Requires-Dist: psycopg2-binary (>=2.9.6,<3.0.0)
Requires-Dist: pytest (>=7.3.0,<8.0.0)
Requires-Dist: pytest-playwright (>=0.4.2,<0.5.0)
Requires-Dist: pyyaml (>=6.0,<7.0)
Requires-Dist: requests (>=2.28.2,<3.0.0)
Requires-Dist: responses (>=0.23.1,<0.24.0)
Requires-Dist: sqlalchemy (>=2.0.17,<3.0.0)
Requires-Dist: stytch (>=6.8.0,<7.0.0)
Requires-Dist: tiktoken (>=0.4.0,<0.5.0)
Requires-Dist: types-flask-migrate (>=4.0.0.3,<5.0.0.0)
Requires-Dist: types-requests (>=2.28.11.17,<3.0.0.0)
